dbdiff/__init__.py
dbdiff/__main__.py
dbdiff/cli.py
dbdiff/logging.json
dbdiff/main.py
dbdiff/report.py
dbdiff/vertica.py
dbdiff/templates/all_keys_count.sql
dbdiff/templates/all_keys_sample.sql
dbdiff/templates/create_dedup.sql
dbdiff/templates/create_dup.sql
dbdiff/templates/create_joined_table.sql
dbdiff/templates/create_joined_table_from_selectinto.sql
dbdiff/templates/create_temp_table.sql
dbdiff/templates/diff_column.sql
dbdiff/templates/diff_column_hier.sql
dbdiff/templates/diff_column_numeric_diffs_binned.sql
dbdiff/templates/diff_column_numeric_diffs_sorted.sql
dbdiff/templates/diff_column_raw.sql
dbdiff/templates/diff_column_summary.sql
dbdiff/templates/diff_rows_sample.sql
dbdiff/templates/first_key_base.sql
dbdiff/templates/first_key_count.sql
dbdiff/templates/first_key_sample.sql
dbdiff/templates/insert_diff.sql
dbdiff/templates/insert_joined_table.sql
dbdiff/templates/joined_column.sql
dbdiff/templates/joined_column_hier.sql
dbdiff/templates/joined_column_numeric_diffs_binned.sql
dbdiff/templates/joined_column_numeric_diffs_sorted.sql
dbdiff/templates/joined_column_raw.sql
dbdiff/templates/joined_count.sql
dbdiff/templates/joined_rows_count.sql
dbdiff/templates/joined_rows_sample.sql
dbdiff/templates/sub_keys_base.sql
dbdiff/templates/sub_keys_count.sql
dbdiff/templates/sub_keys_grouped.sql
dbdiff/templates/sub_keys_sample.sql
dbdiff/templates/table_columns.sql
dbdiff/templates/table_drop.sql
dbdiff/templates/table_exists.sql
dbdiff/templates/table_rows.sql
dbdiff/templates/table_rows_uniq.sql
dbdiff/templates/html/base.html
dbdiff/templates/html/report.html
dbdiff-0.7.0.dist-info/licenses/AUTHORS.md
dbdiff-0.7.0.dist-info/licenses/LICENSE
dbdiff-0.7.0.dist-info/METADATA
dbdiff-0.7.0.dist-info/WHEEL
dbdiff-0.7.0.dist-info/entry_points.txt
dbdiff-0.7.0.dist-info/top_level.txt
dbdiff-0.7.0.dist-info/RECORD
