Metadata-Version: 2.4
Name: dbdiff
Version: 0.7.0
Summary: Compare two tables on Vertica.
Home-page: https://github.com/andyreagan/dbdiff
Author: Andy Reagan
Author-email: andy@andyreagan.com
License: MIT
Project-URL: Issue Tracker, https://github.com/andyreagan/dbdiff/issues
Classifier: Development Status :: 5 - Production/Stable
Classifier: Intended Audience :: Developers
Classifier: License :: OSI Approved :: MIT License
Classifier: Operating System :: Unix
Classifier: Operating System :: POSIX
Classifier: Programming Language :: Python
Classifier: Programming Language :: Python :: 3
Classifier: Programming Language :: Python :: 3.9
Classifier: Programming Language :: Python :: 3.10
Classifier: Programming Language :: Python :: 3.11
Classifier: Programming Language :: Python :: 3.12
Classifier: Topic :: Utilities
Requires-Python: >=3.9
License-File: LICENSE
License-File: AUTHORS.md
Requires-Dist: click
Requires-Dist: requests
Requires-Dist: pandas>=1.0.0
Requires-Dist: Jinja2
Requires-Dist: python-dotenv
Requires-Dist: vertica_python
Requires-Dist: xlsxwriter
Dynamic: author
Dynamic: author-email
Dynamic: classifier
Dynamic: description
Dynamic: description-content-type
Dynamic: home-page
Dynamic: license
Dynamic: license-file
Dynamic: project-url
Dynamic: requires-dist
Dynamic: requires-python
Dynamic: summary
